setup.py
simpledependency/__init__.py
simpledependency/decorator.py
simpledependency/dependency_store.py
simpledependency.egg-info/PKG-INFO
simpledependency.egg-info/SOURCES.txt
simpledependency.egg-info/dependency_links.txt
simpledependency.egg-info/top_level.txt