Metadata-Version: 1.0
Name: simpledependency
Version: 0.0.1
Summary: An embarrassingly simple library for replacing dependencies.
Home-page: https://github.com/attachmentsme/simpledependency
Author: Benjamin Coe
Author-email: ben@attachments.me
License: UNKNOWN
Platform: UNKNOWN
